openbb_benzinga/__init__.py
openbb_benzinga/models/__init__.py
openbb_benzinga/models/analyst_search.py
openbb_benzinga/models/company_news.py
openbb_benzinga/models/price_target.py
openbb_benzinga/models/world_news.py
openbb_benzinga/py.typed
openbb_benzinga/utils/__init__.py
openbb_benzinga/utils/helpers.py
openbb_benzinga-1.4.1.dist-info/METADATA
openbb_benzinga-1.4.1.dist-info/WHEEL
openbb_benzinga-1.4.1.dist-info/entry_points.txt
openbb_benzinga-1.4.1.dist-info/RECORD
